Metadata-Version: 2.1
Name: messenger-server-from-nadezhda
Version: 0.3.0
Summary: Server packet
Home-page: UNKNOWN
Author: Nadezhda Vlasova
Author-email: nadvlasova@rambler.ru
License: UNKNOWN
Platform: UNKNOWN
Requires-Dist: PyQt5
Requires-Dist: pycryptodome
Requires-Dist: pycryptodomex
Requires-Dist: sqlalchemy
